pymhm/Makefile
pymhm/README.html
pymhm/README.txt
pymhm/__init__.py
pymhm/cli.py
pymhm/icon.png
pymhm/metadata.txt
pymhm/pb_tool.cfg
pymhm/plugin_upload.py
pymhm/pylintrc
pymhm/pymhm.py
pymhm/pymhm_dialog.py
pymhm/pymhm_dialog_base.ui
pymhm/resources.py
pymhm/resources.qrc
pymhm/ui_pymhm_dialog_base.py
pymhm/help/Makefile
pymhm/help/make.bat
pymhm/help/source/conf.py
pymhm/help/source/index.rst
pymhm/i18n/af.ts
pymhm/scripts/compile-strings.sh
pymhm/scripts/run-env-linux.sh
pymhm/scripts/update-strings.sh
pymhm/test/__init__.py
pymhm/test/qgis_interface.py
pymhm/test/tenbytenraster.asc
pymhm/test/tenbytenraster.asc.aux.xml
pymhm/test/tenbytenraster.keywords
pymhm/test/tenbytenraster.lic
pymhm/test/tenbytenraster.prj
pymhm/test/tenbytenraster.qml
pymhm/test/test_init.py
pymhm/test/test_pymhm_dialog.py
pymhm/test/test_qgis_environment.py
pymhm/test/test_resources.py
pymhm/test/test_translations.py
pymhm/test/utilities.py
pymhm-0.1.0.dist-info/LICENSE
pymhm-0.1.0.dist-info/METADATA
pymhm-0.1.0.dist-info/WHEEL
pymhm-0.1.0.dist-info/entry_points.txt
pymhm-0.1.0.dist-info/top_level.txt
pymhm-0.1.0.dist-info/RECORD
