Metadata-Version: 2.2
Name: pymhm
Version: 0.1.0
Summary: Python package for mesoscale Hydrological Model
Home-page: https://github.com/SanjeevBashyal/pymhm
Author: Sanjeev Bashyal
Author-email: Sanjeev Bashyal <sanjeev.bashyal01@gmail.com>
Maintainer-email: Sanjeev Bashyal <sanjeev.bashyal01@gmail.com>
License: GPL-2.0
Project-URL: Homepage, https://github.com/SanjeevBashyal/pymhm
Project-URL: Documentation, https://github.com/SanjeevBashyal/pymhm/wiki
Project-URL: Repository, https://github.com/SanjeevBashyal/pymhm
Project-URL: Bug Tracker, https://github.com/SanjeevBashyal/pymhm/issues
Keywords: hydrology,modeling,mesoscale,water,environment,qgis,plugin
Classifier: Development Status :: 3 - Alpha
Classifier: Intended Audience :: Science/Research
Classifier: Topic :: Scientific/Engineering :: Hydrology
Classifier: License :: OSI Approved :: GNU General Public License v2 (GPLv2)
Classifier: Programming Language :: Python :: 3
Classifier: Programming Language :: Python :: 3.8
Classifier: Programming Language :: Python :: 3.9
Classifier: Programming Language :: Python :: 3.10
Classifier: Programming Language :: Python :: 3.11
Classifier: Programming Language :: Python :: 3.12
Classifier: Operating System :: OS Independent
Requires-Python: >=3.8
License-File: LICENSE
Requires-Dist: numpy>=1.20.0
Requires-Dist: scipy>=1.7.0
Requires-Dist: pandas>=1.3.0
Provides-Extra: dev
Requires-Dist: pytest>=6.0; extra == "dev"
Requires-Dist: pytest-cov; extra == "dev"
Requires-Dist: black; extra == "dev"
Requires-Dist: flake8; extra == "dev"
Requires-Dist: mypy; extra == "dev"
Provides-Extra: docs
Requires-Dist: sphinx; extra == "docs"
Requires-Dist: sphinx-rtd-theme; extra == "docs"
Provides-Extra: viz
Requires-Dist: matplotlib>=3.3.0; extra == "viz"
Requires-Dist: netCDF4>=1.5.0; extra == "viz"
Requires-Dist: xarray>=0.19.0; extra == "viz"
Dynamic: author
Dynamic: home-page
Dynamic: requires-python
